nOmicron/__init__.py
nOmicron/mate/__init__.py
nOmicron/mate/mate.py
nOmicron/mate/objects.py
nOmicron/microscope/IO.py
nOmicron/microscope/PLL.py
nOmicron/microscope/__init__.py
nOmicron/microscope/conditioning.py
nOmicron/microscope/continuous_spectroscopy.py
nOmicron/microscope/tip_approaching.py
nOmicron/microscope/xy_scanner.py
nOmicron/utils/__init__.py
nOmicron/utils/debug.py
nOmicron/utils/plotting.py
nOmicron/utils/utils.py
nOmicron-1.3.0.dist-info/LICENSE.txt
nOmicron-1.3.0.dist-info/METADATA
nOmicron-1.3.0.dist-info/WHEEL
nOmicron-1.3.0.dist-info/top_level.txt
nOmicron-1.3.0.dist-info/RECORD
